playwright_booster/__init__.py
playwright_booster/main.py
playwright_booster-0.0.1.dist-info/METADATA
playwright_booster-0.0.1.dist-info/WHEEL
playwright_booster-0.0.1.dist-info/licenses/LICENSE
playwright_booster-0.0.1.dist-info/RECORD
